<?xml version="1.0" encoding="UTF-8" standalone="yes"?>
<domain ASID="10002" xmlns:xsi="http://www.w3.org/2001/XMLSchema-instance" xsi:noNamespaceSchemaLocation="http://totem.run.montefiore.ulg.ac.be/Schema/Domain-v1_3.xsd">
    <info>
        <title>Test Topology</title>
        <date>2004-04-07</date>
        <author>RUN - University of Liege</author>
        <description>
			Perl script of the Research Unit in Networking (RUN) of the University of Liege
			TOTEM Project (http://totem.info.ucl.ac.be/)
		</description>
        <units>
            <unit type="bandwidth" value="kbps"/>
            <unit type="delay" value="ms"/>
        </units>
        <diff-serv>
            <priority ct="0" id="0" preemption="0"/>
            <priority ct="0" id="1" preemption="1"/>
            <priority ct="1" id="4" preemption="0"/>
            <priority ct="1" id="5" preemption="1"/>
            <priority ct="1" id="6" preemption="2"/>
            <priority ct="1" id="7" preemption="3"/>
        </diff-serv>
    </info>
    <topology>
        <nodes>
            <node id="0">
                <status>UP</status>
                <location latitude="417.27148" longitude="209.90099"/>
                <interfaces>
                    <interface id="0"/>
                </interfaces>
            </node>
            <node id="1">
                <status>UP</status>
                <location latitude="639.0969" longitude="209.89328"/>
                <interfaces>
                    <interface id="1"/>
                </interfaces>
            </node>
            <node id="2">
                <status>UP</status>
                <location latitude="540.0969" longitude="404.67984"/>
                <interfaces>
                    <interface id="0"/>
                    <interface id="1"/>
                    <interface id="2"/>
                </interfaces>
            </node>
            <node id="3">
                <status>UP</status>
                <location latitude="370.84488" longitude="686.088"/>
                <interfaces>
                    <interface id="3"/>
                    <interface id="4"/>
                </interfaces>
            </node>
            <node id="4">
                <status>UP</status>
                <location latitude="730.7257" longitude="686.1078"/>
                <interfaces>
                    <interface id="2"/>
                    <interface id="4"/>
                </interfaces>
            </node>
            <node id="2bis">
                <status>UP</status>
                <location latitude="542.57855" longitude="523.6123"/>
                <interfaces>
                    <interface id="2"/>
                    <interface id="3"/>
                    <interface id="4"/>
                </interfaces>
            </node>
        </nodes>
        <links>
            <link id="0_0 -&gt; 2_0">
                <from if="0" node="0"/>
                <to if="0" node="2"/>
                <status>UP</status>
                <bw>200000.0</bw>
                <delay>1.4270346</delay>
            </link>
            <link id="2_0 -&gt; 0_0">
                <from if="0" node="2"/>
                <to if="0" node="0"/>
                <status>UP</status>
                <bw>200000.0</bw>
                <delay>1.4270346</delay>
            </link>
            <link id="1_1 -&gt; 2_1">
                <from if="1" node="1"/>
                <to if="1" node="2"/>
                <status>UP</status>
                <bw>200000.0</bw>
                <delay>1.4270346</delay>
            </link>
            <link id="2_1 -&gt; 1_1">
                <from if="1" node="2"/>
                <to if="1" node="1"/>
                <status>UP</status>
                <bw>200000.0</bw>
                <delay>1.4270346</delay>
            </link>
            <link id="4_2 -&gt; 2b_4">
                <from if="2" node="4"/>
                <to if="4" node="2bis"/>
                <status>UP</status>
                <bw>200000.0</bw>
                <delay>1.4270346</delay>
            </link>
            <link id="2b_4 -&gt; 4_2">
                <from if="4" node="2bis"/>
                <to if="2" node="4"/>
                <status>UP</status>
                <bw>200000.0</bw>
                <delay>1.4270346</delay>
            </link>
            <link id="3_3 -&gt; 2b_3">
                <from if="3" node="3"/>
                <to if="3" node="2bis"/>
                <status>UP</status>
                <bw>200000.0</bw>
                <delay>1.4270346</delay>
            </link>
            <link id="2b_3 -&gt; 3_3">
                <from if="3" node="2bis"/>
                <to if="3" node="3"/>
                <status>UP</status>
                <bw>200000.0</bw>
                <delay>1.4270346</delay>
            </link>
            <link id="3_4 -&gt; 4_4">
                <from if="4" node="3"/>
                <to if="4" node="4"/>
                <status>UP</status>
                <bw>200000.0</bw>
                <delay>1.4270346</delay>
            </link>
            <link id="4_4 -&gt; 3_4">
                <from if="4" node="4"/>
                <to if="4" node="3"/>
                <status>UP</status>
                <bw>200000.0</bw>
                <delay>1.4270346</delay>
            </link>
            <link id="2_2 -&gt; 2b_2">
                <from if="2" node="2"/>
                <to if="2" node="2bis"/>
                <status>UP</status>
                <bw>200000.0</bw>
                <delay>1.4270346</delay>
            </link>
            <link id="2b_2 -&gt; 2_2">
                <from if="2" node="2bis"/>
                <to if="2" node="2"/>
                <status>UP</status>
                <bw>200000.0</bw>
                <delay>1.4270346</delay>
            </link>
        </links>
    </topology>
    <igp>
        <links>
            <link id="0_0 -&gt; 2_0">
                <static>
                    <metric>5.0E-6</metric>
                    <te-metric>5.0E-6</te-metric>
                    <mrbw>200000.0</mrbw>
                    <mbw>200000.0</mbw>
                    <diff-serv>
                        <bcm>MAM</bcm>
                        <bc id="0">150000.0</bc>
                        <bc id="1">50000.0</bc>
                    </diff-serv>
                </static>
                <dynamic>
                    <rbw>
                        <priority id="0">150000.0</priority>
                        <priority id="1">150000.0</priority>
                        <priority id="4">50000.0</priority>
                        <priority id="5">50000.0</priority>
                        <priority id="6">50000.0</priority>
                        <priority id="7">50000.0</priority>
                    </rbw>
                </dynamic>
            </link>
            <link id="2_0 -&gt; 0_0">
                <static>
                    <metric>5.0E-6</metric>
                    <te-metric>5.0E-6</te-metric>
                    <mrbw>200000.0</mrbw>
                    <mbw>200000.0</mbw>
                    <diff-serv>
                        <bcm>MAM</bcm>
                        <bc id="0">150000.0</bc>
                        <bc id="1">50000.0</bc>
                    </diff-serv>
                </static>
                <dynamic>
                    <rbw>
                        <priority id="0">150000.0</priority>
                        <priority id="1">150000.0</priority>
                        <priority id="4">50000.0</priority>
                        <priority id="5">50000.0</priority>
                        <priority id="6">50000.0</priority>
                        <priority id="7">50000.0</priority>
                    </rbw>
                </dynamic>
            </link>
            <link id="1_1 -&gt; 2_1">
                <static>
                    <metric>5.0E-6</metric>
                    <te-metric>5.0E-6</te-metric>
                    <mrbw>200000.0</mrbw>
                    <mbw>200000.0</mbw>
                    <diff-serv>
                        <bcm>MAM</bcm>
                        <bc id="0">150000.0</bc>
                        <bc id="1">50000.0</bc>
                    </diff-serv>
                </static>
                <dynamic>
                    <rbw>
                        <priority id="0">150000.0</priority>
                        <priority id="1">150000.0</priority>
                        <priority id="4">50000.0</priority>
                        <priority id="5">50000.0</priority>
                        <priority id="6">50000.0</priority>
                        <priority id="7">50000.0</priority>
                    </rbw>
                </dynamic>
            </link>
            <link id="2_1 -&gt; 1_1">
                <static>
                    <metric>5.0E-6</metric>
                    <te-metric>5.0E-6</te-metric>
                    <mrbw>200000.0</mrbw>
                    <mbw>200000.0</mbw>
                    <diff-serv>
                        <bcm>MAM</bcm>
                        <bc id="0">150000.0</bc>
                        <bc id="1">50000.0</bc>
                    </diff-serv>
                </static>
                <dynamic>
                    <rbw>
                        <priority id="0">150000.0</priority>
                        <priority id="1">150000.0</priority>
                        <priority id="4">50000.0</priority>
                        <priority id="5">50000.0</priority>
                        <priority id="6">50000.0</priority>
                        <priority id="7">50000.0</priority>
                    </rbw>
                </dynamic>
            </link>
            <link id="4_2 -&gt; 2b_4">
                <static>
                    <metric>5.0E-6</metric>
                    <te-metric>5.0E-6</te-metric>
                    <mrbw>200000.0</mrbw>
                    <mbw>200000.0</mbw>
                    <diff-serv>
                        <bcm>MAM</bcm>
                        <bc id="0">150000.0</bc>
                        <bc id="1">50000.0</bc>
                    </diff-serv>
                </static>
                <dynamic>
                    <rbw>
                        <priority id="0">150000.0</priority>
                        <priority id="1">150000.0</priority>
                        <priority id="4">50000.0</priority>
                        <priority id="5">50000.0</priority>
                        <priority id="6">50000.0</priority>
                        <priority id="7">50000.0</priority>
                    </rbw>
                </dynamic>
            </link>
            <link id="2b_4 -&gt; 4_2">
                <static>
                    <metric>5.0E-6</metric>
                    <te-metric>5.0E-6</te-metric>
                    <mrbw>200000.0</mrbw>
                    <mbw>200000.0</mbw>
                    <diff-serv>
                        <bcm>MAM</bcm>
                        <bc id="0">150000.0</bc>
                        <bc id="1">50000.0</bc>
                    </diff-serv>
                </static>
                <dynamic>
                    <rbw>
                        <priority id="0">150000.0</priority>
                        <priority id="1">150000.0</priority>
                        <priority id="4">50000.0</priority>
                        <priority id="5">50000.0</priority>
                        <priority id="6">50000.0</priority>
                        <priority id="7">50000.0</priority>
                    </rbw>
                </dynamic>
            </link>
            <link id="3_3 -&gt; 2b_3">
                <static>
                    <metric>1.0E-5</metric>
                    <te-metric>1.0E-5</te-metric>
                    <mrbw>200000.0</mrbw>
                    <mbw>200000.0</mbw>
                    <diff-serv>
                        <bcm>MAM</bcm>
                        <bc id="0">150000.0</bc>
                        <bc id="1">50000.0</bc>
                    </diff-serv>
                </static>
                <dynamic>
                    <rbw>
                        <priority id="0">150000.0</priority>
                        <priority id="1">150000.0</priority>
                        <priority id="4">50000.0</priority>
                        <priority id="5">50000.0</priority>
                        <priority id="6">50000.0</priority>
                        <priority id="7">50000.0</priority>
                    </rbw>
                </dynamic>
            </link>
            <link id="2b_3 -&gt; 3_3">
                <static>
                    <metric>1.0E-5</metric>
                    <te-metric>1.0E-5</te-metric>
                    <mrbw>200000.0</mrbw>
                    <mbw>200000.0</mbw>
                    <diff-serv>
                        <bcm>MAM</bcm>
                        <bc id="0">150000.0</bc>
                        <bc id="1">50000.0</bc>
                    </diff-serv>
                </static>
                <dynamic>
                    <rbw>
                        <priority id="0">150000.0</priority>
                        <priority id="1">150000.0</priority>
                        <priority id="4">50000.0</priority>
                        <priority id="5">50000.0</priority>
                        <priority id="6">50000.0</priority>
                        <priority id="7">50000.0</priority>
                    </rbw>
                </dynamic>
            </link>
            <link id="3_4 -&gt; 4_4">
                <static>
                    <metric>1.0E-5</metric>
                    <te-metric>1.0E-5</te-metric>
                    <mrbw>200000.0</mrbw>
                    <mbw>200000.0</mbw>
                    <diff-serv>
                        <bcm>MAM</bcm>
                        <bc id="0">150000.0</bc>
                        <bc id="1">50000.0</bc>
                    </diff-serv>
                </static>
                <dynamic>
                    <rbw>
                        <priority id="0">150000.0</priority>
                        <priority id="1">150000.0</priority>
                        <priority id="4">50000.0</priority>
                        <priority id="5">50000.0</priority>
                        <priority id="6">50000.0</priority>
                        <priority id="7">50000.0</priority>
                    </rbw>
                </dynamic>
            </link>
            <link id="4_4 -&gt; 3_4">
                <static>
                    <metric>1.0E-5</metric>
                    <te-metric>1.0E-5</te-metric>
                    <mrbw>200000.0</mrbw>
                    <mbw>200000.0</mbw>
                    <diff-serv>
                        <bcm>MAM</bcm>
                        <bc id="0">150000.0</bc>
                        <bc id="1">50000.0</bc>
                    </diff-serv>
                </static>
                <dynamic>
                    <rbw>
                        <priority id="0">150000.0</priority>
                        <priority id="1">150000.0</priority>
                        <priority id="4">50000.0</priority>
                        <priority id="5">50000.0</priority>
                        <priority id="6">50000.0</priority>
                        <priority id="7">50000.0</priority>
                    </rbw>
                </dynamic>
            </link>
            <link id="2_2 -&gt; 2b_2">
                <static>
                    <metric>1.0E-5</metric>
                    <te-metric>1.0E-5</te-metric>
                    <mrbw>200000.0</mrbw>
                    <mbw>200000.0</mbw>
                    <diff-serv>
                        <bcm>MAM</bcm>
                        <bc id="0">150000.0</bc>
                        <bc id="1">50000.0</bc>
                    </diff-serv>
                </static>
                <dynamic>
                    <rbw>
                        <priority id="0">150000.0</priority>
                        <priority id="1">150000.0</priority>
                        <priority id="4">50000.0</priority>
                        <priority id="5">50000.0</priority>
                        <priority id="6">50000.0</priority>
                        <priority id="7">50000.0</priority>
                    </rbw>
                </dynamic>
            </link>
            <link id="2b_2 -&gt; 2_2">
                <static>
                    <metric>1.0E-5</metric>
                    <te-metric>1.0E-5</te-metric>
                    <mrbw>200000.0</mrbw>
                    <mbw>200000.0</mbw>
                    <diff-serv>
                        <bcm>MAM</bcm>
                        <bc id="0">150000.0</bc>
                        <bc id="1">50000.0</bc>
                    </diff-serv>
                </static>
                <dynamic>
                    <rbw>
                        <priority id="0">150000.0</priority>
                        <priority id="1">150000.0</priority>
                        <priority id="4">50000.0</priority>
                        <priority id="5">50000.0</priority>
                        <priority id="6">50000.0</priority>
                        <priority id="7">50000.0</priority>
                    </rbw>
                </dynamic>
            </link>
        </links>
    </igp>
</domain>

